dropbox/__init__.py
dropbox/account.py
dropbox/async.py
dropbox/async_.py
dropbox/auth.py
dropbox/base.py
dropbox/base_team.py
dropbox/check.py
dropbox/common.py
dropbox/contacts.py
dropbox/dropbox_client.py
dropbox/exceptions.py
dropbox/file_properties.py
dropbox/file_requests.py
dropbox/files.py
dropbox/oauth.py
dropbox/openid.py
dropbox/paper.py
dropbox/secondary_emails.py
dropbox/seen_state.py
dropbox/session.py
dropbox/sharing.py
dropbox/stone_base.py
dropbox/stone_serializers.py
dropbox/stone_validators.py
dropbox/team.py
dropbox/team_common.py
dropbox/team_log.py
dropbox/team_policies.py
dropbox/users.py
dropbox/users_common.py
dropbox-12.0.2.dist-info/LICENSE
dropbox-12.0.2.dist-info/METADATA
dropbox-12.0.2.dist-info/WHEEL
dropbox-12.0.2.dist-info/top_level.txt
dropbox-12.0.2.dist-info/RECORD
