Metadata-Version: 2.1
Name: dropbox
Version: 12.0.2
Summary: Official Dropbox API Client
Home-page: http://www.dropbox.com/developers
Author: Dropbox
Author-email: dev-platform@dropbox.com
License: MIT License
Project-URL: Source, https://github.com/dropbox/dropbox-sdk-python
Platform: UNKNOWN
Classifier: Development Status :: 5 - Production/Stable
Classifier: Intended Audience :: Developers
Classifier: License :: OSI Approved :: MIT License
Classifier: Operating System :: OS Independent
Classifier: Programming Language :: Python
Classifier: Programming Language :: Python :: 2.7
Classifier: Programming Language :: Python :: 3.4
Classifier: Programming Language :: Python :: 3.5
Classifier: Programming Language :: Python :: 3.6
Classifier: Programming Language :: Python :: 3.7
Classifier: Programming Language :: Python :: 3.8
Classifier: Programming Language :: Python :: Implementation :: CPython
Classifier: Programming Language :: Python :: Implementation :: PyPy
Classifier: Topic :: Software Development :: Libraries :: Python Modules
Requires-Dist: requests (>=2.16.2)
Requires-Dist: six (>=1.12.0)
Requires-Dist: stone (<3.3.3,>=2)
